fixturepy/__init__.py
fixturepy-0.5.dist-info/LICENSE.txt
fixturepy-0.5.dist-info/METADATA
fixturepy-0.5.dist-info/WHEEL
fixturepy-0.5.dist-info/top_level.txt
fixturepy-0.5.dist-info/RECORD
