Metadata-Version: 2.1
Name: fixturepy
Version: 0.5
Summary: Create random data to be used in tests
Home-page: https://github.com/exentriquesolutions/fixturepy
Author: Exentrique Solutions
Author-email: rs@exentriquesolutions.com
License: MIT
Keywords: UnitTest,Fixture
Platform: UNKNOWN
Classifier: Development Status :: 3 - Alpha
Classifier: Intended Audience :: Developers
Classifier: Topic :: Software Development :: Testing :: Unit
Classifier: License :: OSI Approved :: MIT License
Classifier: Programming Language :: Python :: 2.7
Classifier: Programming Language :: Python :: 3
Classifier: Programming Language :: Python :: 3.5
Classifier: Programming Language :: Python :: 3.6
Classifier: Programming Language :: Python :: 3.7
Classifier: Programming Language :: Python :: 3.8
Provides-Extra: test
Requires-Dist: assertpy ; extra == 'test'
Requires-Dist: email-validator ; extra == 'test'
